object_position_calculator/CoordinateCalculator.py
object_position_calculator/__init__.py
object_position_calculator/calculate.py
object_position_calculator/detect_object.py
object_position_calculator/newCalculator.py
object_position_calculator/object_position.py
object_position_calculator/position_calculator.py
coordinate_calculator-0.1.6.dist-info/LICENSE
coordinate_calculator-0.1.6.dist-info/METADATA
coordinate_calculator-0.1.6.dist-info/WHEEL
coordinate_calculator-0.1.6.dist-info/top_level.txt
coordinate_calculator-0.1.6.dist-info/RECORD
